{
  "slug": "kokopelli-vcv",
  "name": "Kokopelli Vcv",
  "version": "2.0",
  "license": "MIT",
  "author": "Michael Muszynski",
  "brand": "Kokopelli Interfaces",
  "authorEmail": "michael.ampm@gmail.com",
  "authorUrl": "",
  "pluginUrl": "",
  "manualUrl": "",
  "sourceUrl": "",
  "donateUrl": "https://ko-fi.com/michaelmuszynski",
  "modules": [
    {
      "slug": "KokopelliInterfaces-Circle",
      "name": "Circle",
      "description": "A general purpose audio layerer which enables a new composition workflow based in live-creation.\n Made with care to be a reflection of that which eminates the universe.",
      "tags": [
        "Poly",
        "Recording",
        "Sampler"
      ]
    }
  ]
}
